{
    "Contact": {
        "es": "Contacto"
    },
    "Contact Us": {
        "es": "Contáctanos"
    },
    "Home": {
        "es": "Inicio"
    },
    "Hosting": {
        "es": "Hospedaje"
    },
    "Blog": {
        "es": "Blog"
    },
    "Domain": {
        "es": "Dominio"
    },
    "Address": {
        "es": "Dirección"
    },
    "Phone": {
        "es": "Télefono"
    },
    "Email Address": {
        "es": "Correo Eléctronico"
    },
    "Email": {
        "es": "Correo Eléctronico"
    },
    "More Info": {
        "es": "Más Información"
    },
    "Contact Info": {
        "es": "Contacto"
    },
    "Shared Hosting": {
        "es": "Hospedaje Compartido"
    },
    "Dedicated Hosting": {
        "es": "Hospedaje Dedicado"
    },
    "Premium Hosting": {
        "es": "Hospedaje Premium"
    },
    "Cloud Hosting": {
        "es": "Hospedaje Nube"
    },
    "24/7 Support": {
        "es": "Soporte 24x7"
    },
    "Live Chat": {
        "es": "Chat en Vivo"
    }, 
    "Chat With Us Now": {
        "es": "Chatea con nosotros"
    }, 
    "Domain Features": {
        "es": "Características del dominio"
    }, 
    "Search": {
        "es": "Buscar"
    }, 
    "Plans start at ": {
        "es": "Planes desde "
    }, 
    "/month": {     
        "es": "/mes"
    }, 
    "View Details": {        
        "es": "Ver Detalles"
    }, 
    "Different hosting platforms to suit every need!": {        
        "es": "¡Diferentes plataformas de alojamiento para adaptarse a cada necesidad!"
    }, 
    "Why Choose Us?": {        
        "es": "¿Por Qué Elegirnos?"
    }, 
    "Amazing Uptime": {        
        "es": "Estabilidad Increíble"
    }, 
    "Best Support": {        
        "es": "Mejor Soporte"
    }, 
    "Client Reviews": {        
        "es": "Testimonios de Clientes"
    }, 
    "High Quality Hardware": {        
        "es": "Hardware de Alta Calidad"
    }, 
    "Top Data Centers": {        
        "es": "Mejores Centros De Datos"
    }, 
    "Outstanding Speed": {        
        "es": "Velocidad Excepcional"
    }, 
    "Testimonials": {        
        "es": "Testimonios"
    }, 
    "Get In Touch": {        
        "es": "Mantente en Contacto"
    }, 
    "Affordable Domains": {        
        "es": "Dominios asequibles"
    }, 
    "Customer Support": {        
        "es": "Atención al cliente"
    }    
    
}